{
  "type": "Feature",
  "properties": {
    "gn:admin1_code":"06",
    "gn:asciiname":"Table Hill Gordon",
    "gn:country_code":"AG",
    "gn:dem":1,
    "gn:feature_class":"P",
    "gn:feature_code":"PPL",
    "gn:name":"Table Hill Gordon",
    "gn:population":0,
    "gn:timezone":"America/Antigua",
    "iso:country":"AG",
    "wof:name":"Table Hill Gordon",
    "wof:placetype":"locality"
},
  "geometry": {"coordinates":[-61.77991,17.04332],"type":"Point"}
}