{
  "type": "Feature",
  "properties": {
    "iso:country":"AG",
    "qs:gn_pop":0,
    "qs:name":"Big Duers",
    "qs:name_adm0":"Antigua and Barbuda",
    "qs:name_adm1":"Saint Peter",
    "qs:photos":4,
    "qs:photos_1k":1,
    "qs:photos_9k":1,
    "qs:photos_9r":1,
    "qs:photos_all":4,
    "qs:photos_sr":1,
    "qs:placetype":"Town",
    "qs:pop_sr":"0",
    "qs:woe_adm0":23424737,
    "wof:name":"Big Duers",
    "wof:placetype":"locality"
},
  "geometry": {"coordinates":[-61.7810965,17.07666],"type":"Point"}
}