{
  "type": "Feature",
  "properties": {
    "gn:admin1_code":"05",
    "gn:asciiname":"Johnsons Point",
    "gn:cc2":"AG",
    "gn:country_code":"AG",
    "gn:dem":7,
    "gn:feature_class":"P",
    "gn:feature_code":"PPL",
    "gn:name":"Johnsons Point",
    "gn:population":0,
    "gn:timezone":"America/Antigua",
    "iso:country":"AG",
    "name:rus_x_preferred":[
        "\u0414\u0436\u043e\u043d\u0441\u043e\u043d\u0441-\u041f\u043e\u0438\u043d\u0442"
    ],
    "name:und_x_variant":[
        "Johnson Point",
        "Johnson Point Village",
        "Johnsons Point"
    ],
    "wof:name":"Johnsons Point",
    "wof:placetype":"locality"
},
  "geometry": {"coordinates":[-61.88885,17.02985],"type":"Point"}
}