{
  "type": "Feature",
  "properties": {
    "gn:admin1_code":"07",
    "gn:asciiname":"Little Duers",
    "gn:country_code":"AG",
    "gn:dem":1,
    "gn:feature_class":"P",
    "gn:feature_code":"PPL",
    "gn:name":"Little Duers",
    "gn:population":0,
    "gn:timezone":"America/Antigua",
    "iso:country":"AG",
    "name:und_x_variant":[
        "Little Duer",
        "Little Duers"
    ],
    "wof:name":"Little Duers",
    "wof:placetype":"locality"
},
  "geometry": {"coordinates":[-61.74761,17.06927],"type":"Point"}
}