{
  "type": "Feature",
  "properties": {
    "gn:admin1_code":"08",
    "gn:asciiname":"Watsons",
    "gn:country_code":"AG",
    "gn:dem":1,
    "gn:feature_class":"P",
    "gn:feature_code":"PPL",
    "gn:name":"Watsons",
    "gn:population":0,
    "gn:timezone":"America/Antigua",
    "iso:country":"AG",
    "name:ara_x_preferred":[
        "\u0648\u0627\u062a\u0633\u0648\u0646"
    ],
    "name:fra_x_preferred":[
        "Watsons"
    ],
    "name:jpn_x_preferred":[
        "\u30ef\u30c8\u30bd\u30f3\u30ba"
    ],
    "name:kor_x_preferred":[
        "\uc653\uc2a8\uc2a4"
    ],
    "name:msa_x_preferred":[
        "Watsons"
    ],
    "name:und_x_variant":[
        "Watson",
        "Watsons"
    ],
    "name:wuu_x_preferred":[
        "\u5c48\u81e3\u6c0f"
    ],
    "name:zho_x_preferred":[
        "\u5c48\u81e3\u6c0f\u500b\u4eba\u8b77\u7406\u5e97"
    ],
    "wof:name":"Watsons",
    "wof:placetype":"locality"
},
  "geometry": {"coordinates":[-61.67789000000001,17.05451],"type":"Point"}
}