{
  "type": "Feature",
  "properties": {
    "gn:gn_country":"AG",
    "gn:gn_fcode":"PPL",
    "gn:gn_pop":1668,
    "gn:population":1668,
    "iso:country":"AG",
    "name:cat_x_preferred":[
        "Liberta"
    ],
    "name:dut_x_preferred":[
        "Liberta"
    ],
    "name:eng_x_preferred":[
        "Liberta"
    ],
    "name:fra_x_preferred":[
        "Liberta"
    ],
    "name:fre_x_preferred":[
        "Liberta"
    ],
    "name:glg_x_preferred":[
        "Liberta"
    ],
    "name:gre_x_preferred":[
        "\u039b\u03af\u03bc\u03c0\u03b5\u03c1\u03c4\u03b1"
    ],
    "name:ilo_x_preferred":[
        "Liberta"
    ],
    "name:per_x_preferred":[
        "\u0644\u06cc\u0628\u0631\u062a\u0627"
    ],
    "name:pol_x_preferred":[
        "Liberta"
    ],
    "name:por_x_preferred":[
        "Liberta"
    ],
    "name:rus_x_preferred":[
        "\u041b\u0438\u0431\u0435\u0440\u0442\u0430"
    ],
    "name:spa_x_preferred":[
        "Liberta"
    ],
    "name:swe_x_preferred":[
        "Liberta"
    ],
    "name:unk_x_variant":[
        "Liberta Village"
    ],
    "qs_pg:aaroncc":"AG",
    "qs_pg:gn_country":"AG",
    "qs_pg:gn_fcode":"PPL",
    "qs_pg:gn_pop":1668,
    "qs_pg:name":"Liberta",
    "qs_pg:photos_9r":0,
    "qs_pg:photos_sr":0,
    "qs_pg:pop_sr":3,
    "qs_pg:qs_pg_placetype":"locality",
    "wof:name":"Liberta",
    "wof:placetype":"locality",
    "wof:population":1668
},
  "geometry": {"coordinates":[-61.78333,17.03333],"type":"Point"}
}