{
  "type": "Feature",
  "properties": {
    "gn:admin1_code":"04",
    "gn:asciiname":"Creekside",
    "gn:country_code":"AG",
    "gn:dem":27,
    "gn:feature_class":"P",
    "gn:feature_code":"PPL",
    "gn:name":"Creekside",
    "gn:population":0,
    "gn:timezone":"America/Antigua",
    "iso:country":"AG",
    "name:ceb_x_preferred":[
        "Creekside"
    ],
    "name:deu_x_preferred":[
        "Creekside"
    ],
    "name:ita_x_preferred":[
        "Creekside"
    ],
    "name:nld_x_preferred":[
        "Creekside"
    ],
    "name:pol_x_preferred":[
        "Creekside"
    ],
    "name:por_x_preferred":[
        "Creekside"
    ],
    "name:srp_x_preferred":[
        "\u041a\u0440\u0438\u043a\u0441\u0430\u0458\u0434"
    ],
    "name:swe_x_preferred":[
        "Creekside"
    ],
    "name:ukr_x_preferred":[
        "\u041a\u0440\u0456\u043a\u0441\u0430\u0439\u0434"
    ],
    "name:vol_x_preferred":[
        "Creekside"
    ],
    "wof:name":"Creekside",
    "wof:placetype":"locality"
},
  "geometry": {"coordinates":[-61.85646,17.07902],"type":"Point"}
}