{
  "type": "Feature",
  "properties": {
    "gn:admin1_code":"04",
    "gn:asciiname":"Creekside",
    "gn:country_code":"AG",
    "gn:dem":27,
    "gn:feature_class":"P",
    "gn:feature_code":"PPL",
    "gn:name":"Creekside",
    "gn:population":0,
    "gn:timezone":"America/Antigua",
    "iso:country":"AG",
    "wof:name":"Creekside",
    "wof:placetype":"locality"
},
  "geometry": {"coordinates":[-61.85646,17.07902],"type":"Point"}
}