{
  "type": "Feature",
  "properties": {
    "gn:admin1_code":"07",
    "gn:asciiname":"The Diamond",
    "gn:country_code":"AG",
    "gn:dem":1,
    "gn:feature_class":"P",
    "gn:feature_code":"PPL",
    "gn:name":"The Diamond",
    "gn:population":0,
    "gn:timezone":"America/Antigua",
    "iso:country":"AG",
    "wof:name":"The Diamond",
    "wof:placetype":"locality"
},
  "geometry": {"coordinates":[-61.76047,17.07759],"type":"Point"}
}