{
  "type": "Feature",
  "properties": {
    "gn:admin1_code":"05",
    "gn:asciiname":"Claremont",
    "gn:country_code":"AG",
    "gn:dem":10,
    "gn:feature_class":"P",
    "gn:feature_code":"PPLL",
    "gn:name":"Claremont",
    "gn:population":0,
    "gn:timezone":"America/Antigua",
    "iso:country":"AG",
    "wof:name":"Claremont",
    "wof:placetype":"locality"
},
  "geometry": {"coordinates":[-61.83586,17.02527000000001],"type":"Point"}
}