{
  "type": "Feature",
  "properties": {
    "gn:admin1_code":"08",
    "gn:asciiname":"Glanvilles",
    "gn:country_code":"AG",
    "gn:dem":1,
    "gn:feature_class":"P",
    "gn:feature_code":"PPL",
    "gn:name":"Glanvilles",
    "gn:population":0,
    "gn:timezone":"America/Antigua",
    "iso:country":"AG",
    "wof:name":"Glanvilles",
    "wof:placetype":"locality"
},
  "geometry": {"coordinates":[-61.7252,17.0858],"type":"Point"}
}