{
  "type": "Feature",
  "properties": {
    "gn:admin1_code":"04",
    "gn:asciiname":"Hamiltons",
    "gn:cc2":"AG",
    "gn:country_code":"AG",
    "gn:dem":238,
    "gn:feature_class":"P",
    "gn:feature_code":"PPL",
    "gn:name":"Hamiltons",
    "gn:population":0,
    "gn:timezone":"America/Antigua",
    "iso:country":"AG",
    "name:und_x_variant":[
        "Hamiltons Village",
        "Hamiltons"
    ],
    "wof:name":"Hamiltons",
    "wof:placetype":"locality"
},
  "geometry": {"coordinates":[-61.83333,17.05],"type":"Point"}
}